CHANGELOG.rst
MANIFEST.in
README.rst
setup.py
trelloapi/__init__.py
trelloapi/api.py
trelloapi/endpoints.yaml
trelloapi/make_endpoints.py
trelloapi.egg-info/PKG-INFO
trelloapi.egg-info/SOURCES.txt
trelloapi.egg-info/dependency_links.txt
trelloapi.egg-info/not-zip-safe
trelloapi.egg-info/top_level.txt