Metadata-Version: 1.1
Name: trelloapi
Version: 0.0.1
Summary: autogenerated trello API client for python
Home-page: https://github.com/nilp0inter/trelloapi
Author: Roberto Abdelkader Martínez Pérez
Author-email: robertomartinezp@gmail.com
License: LGPLv3
Keywords: trello api client:q
Platform: UNKNOWN
Classifier: Programming Language :: Python :: 3.4
Classifier: Development Status :: 4 - Beta
Classifier: License :: OSI Approved :: GNU Lesser General Public License v3 (LGPLv3)
